LICENSE
README.rst
setup.cfg
setup.py
slurmpter/__init__.py
slurmpter/job.py
slurmpter/slurm.py
slurmpter.egg-info/PKG-INFO
slurmpter.egg-info/SOURCES.txt
slurmpter.egg-info/dependency_links.txt
slurmpter.egg-info/requires.txt
slurmpter.egg-info/top_level.txt