Metadata-Version: 2.1
Name: slurmpter
Version: 1.0.0
Summary: A package to build Slurm submit files of a workflow of jobs easily.
Home-page: https://gitlab.com/isaac-cfwong/slurmpter
Author: Isaac Chun Fung WONG
Author-email: chunefung@gmail.com
License: MIT
Platform: UNKNOWN
Classifier: Development Status :: 4 - Beta
Classifier: License :: OSI Approved :: MIT License
Classifier: Programming Language :: Python :: 3
Classifier: Operating System :: OS Independent
Requires-Python: >=3.5
